ponders/__init__.py
ponders/_version.py
ponders/ponders.py
ponders/tests/__init__.py
ponders/tests/conftest.py
ponders/tests/test_examples.py
ponders/tests/test_pca.py
ponders/tests/utils.py
ponders-0.2.0.dist-info/AUTHORS.rst
ponders-0.2.0.dist-info/LICENSE
ponders-0.2.0.dist-info/METADATA
ponders-0.2.0.dist-info/WHEEL
ponders-0.2.0.dist-info/entry_points.txt
ponders-0.2.0.dist-info/top_level.txt
ponders-0.2.0.dist-info/RECORD
