Metadata-Version: 2.1
Name: ponders
Version: 0.2.0
Summary: A library to allow scikit-learn to automatically handle Pandas DataFrames
Home-page: https://github.com/claresloggett/ponder
Author: Clare Sloggett
Author-email: claresloggett@gmail.com
License: BSD (3-clause)
Platform: UNKNOWN
Classifier: Development Status :: 2 - Pre-Alpha
Classifier: Natural Language :: English
Classifier: Programming Language :: Python :: 3
License-File: LICENSE
License-File: AUTHORS.rst
Requires-Dist: scikit-learn
Requires-Dist: numpy
Requires-Dist: pandas
